Metadata-Version: 1.2
Name: fb-re2
Version: 1.0.7
Summary: Python wrapper for Google's RE2
Home-page: https://github.com/facebook/pyre2
Author: David Reiss
Author-email: dreiss@fb.com
Maintainer: Siddharth Agarwal
Maintainer-email: sid0@fb.com
License: UNKNOWN
Platform: UNKNOWN
Classifier: Intended Audience :: Developers
Classifier: License :: OSI Approved :: BSD License
Classifier: Development Status :: 5 - Production/Stable
